{"identifier":"crate_crate-jdbc","features":{"ch.uzh.ciclassifier.features.travisci.BuildTimeLatestAverage":"973.96","ch.uzh.ciclassifier.features.repository.NumberOfConfigurationFileChanges":"12","ch.uzh.ciclassifier.features.configuration.UseCache":"1","ch.uzh.ciclassifier.features.repository.NumberOfContributorsOnConfigurationFile":"6","ch.uzh.ciclassifier.features.travisci.BuildSuccessRatio":"0.6070549630844955","ch.uzh.ciclassifier.features.configuration.NumberOfConfigurationLines":"27","ch.uzh.ciclassifier.features.configuration.TemplateSimilarity":"10","ch.uzh.ciclassifier.features.configuration.ParseScore":"11","ch.uzh.ciclassifier.features.repository.NumberOfContributors":"28","ch.uzh.ciclassifier.features.configuration.NumberOfComments":"1","ch.uzh.ciclassifier.features.travisci.TimeToFixLatestAverage":"262446.2","ch.uzh.ciclassifier.features.github.OwnerType":"Organization","ch.uzh.ciclassifier.features.configuration.NumberOfNotifications":"0","ch.uzh.ciclassifier.features.travisci.ManualInteractionRatio":"0.0","ch.uzh.ciclassifier.features.repository.ProjectName":"crate\/crate-jdbc","ch.uzh.ciclassifier.features.repository.DaysUntilConfigAdded":"137","ch.uzh.ciclassifier.features.configuration.LintScore":"1","ch.uzh.ciclassifier.features.configuration.EnvSize":"1","ch.uzh.ciclassifier.features.configuration.UseDeploy":"0","ch.uzh.ciclassifier.features.configuration.NumberOfJobs":"5","ch.uzh.ciclassifier.features.configuration.NumberOfConfigurationChars":"404","ch.uzh.ciclassifier.features.travisci.BuildTimeAverage":"1053.5718654434252","ch.uzh.ciclassifier.features.configuration.UniqueInstructions":"2","ch.uzh.ciclassifier.features.repository.CommitsUntilConfigAdded":"90","ch.uzh.ciclassifier.features.configuration.NumberOfStages":"1","ch.uzh.ciclassifier.features.travisci.PullRequestRatio":"0.6873614190687362","ch.uzh.ciclassifier.features.configuration.UseBranches":"0","ch.uzh.ciclassifier.features.github.PrimaryLanguage":"Java","ch.uzh.ciclassifier.features.repository.ConfigChangeFrequency":"0.03015075376884422","ch.uzh.ciclassifier.features.travisci.TimeToFixAverage":"77252.64"},"types":["REPOSITORY","CONFIGURATION","GITHUB","TRAVISCI"],"db-identifier":"256ff8ec-3054-4636-9cc6-288912971f43"}