{"identifier":"envygeeks_jekyll-assets","features":{"ch.uzh.ciclassifier.features.travisci.BuildTimeLatestAverage":"1951.04","ch.uzh.ciclassifier.features.repository.NumberOfConfigurationFileChanges":"54","ch.uzh.ciclassifier.features.configuration.UseCache":"1","ch.uzh.ciclassifier.features.repository.NumberOfContributorsOnConfigurationFile":"5","ch.uzh.ciclassifier.features.travisci.BuildSuccessRatio":"0.7005758157389635","ch.uzh.ciclassifier.features.configuration.NumberOfConfigurationLines":"42","ch.uzh.ciclassifier.features.configuration.TemplateSimilarity":"11","ch.uzh.ciclassifier.features.configuration.ParseScore":"14","ch.uzh.ciclassifier.features.repository.NumberOfContributors":"83","ch.uzh.ciclassifier.features.configuration.NumberOfComments":"0","ch.uzh.ciclassifier.features.travisci.TimeToFixLatestAverage":"1040975.4","ch.uzh.ciclassifier.features.github.OwnerType":"User","ch.uzh.ciclassifier.features.configuration.NumberOfNotifications":"1","ch.uzh.ciclassifier.features.travisci.ManualInteractionRatio":"0.002061855670103093","ch.uzh.ciclassifier.features.repository.ProjectName":"envygeeks\/jekyll-assets","ch.uzh.ciclassifier.features.repository.DaysUntilConfigAdded":"0","ch.uzh.ciclassifier.features.configuration.LintScore":"1","ch.uzh.ciclassifier.features.configuration.EnvSize":"4","ch.uzh.ciclassifier.features.configuration.UseDeploy":"0","ch.uzh.ciclassifier.features.configuration.NumberOfJobs":"8","ch.uzh.ciclassifier.features.configuration.NumberOfConfigurationChars":"811","ch.uzh.ciclassifier.features.travisci.BuildTimeAverage":"2171.312684365782","ch.uzh.ciclassifier.features.configuration.UniqueInstructions":"4","ch.uzh.ciclassifier.features.repository.CommitsUntilConfigAdded":"0","ch.uzh.ciclassifier.features.configuration.NumberOfStages":"1","ch.uzh.ciclassifier.features.travisci.PullRequestRatio":"0.334020618556701","ch.uzh.ciclassifier.features.configuration.UseBranches":"1","ch.uzh.ciclassifier.features.github.PrimaryLanguage":"Ruby","ch.uzh.ciclassifier.features.repository.ConfigChangeFrequency":"0.03988183161004431","ch.uzh.ciclassifier.features.travisci.TimeToFixAverage":"1154954.177777778"},"types":["REPOSITORY","CONFIGURATION","GITHUB","TRAVISCI"],"db-identifier":"8aa66921-7bf2-4cd6-b831-4c3e23957a39"}