{"identifier":"pypa_pip","features":{"ch.uzh.ciclassifier.features.travisci.BuildTimeLatestAverage":"3993.32","ch.uzh.ciclassifier.features.repository.NumberOfConfigurationFileChanges":"134","ch.uzh.ciclassifier.features.configuration.UseCache":"1","ch.uzh.ciclassifier.features.repository.NumberOfContributorsOnConfigurationFile":"20","ch.uzh.ciclassifier.features.travisci.BuildSuccessRatio":"0.679982343853454","ch.uzh.ciclassifier.features.configuration.NumberOfConfigurationLines":"33","ch.uzh.ciclassifier.features.configuration.TemplateSimilarity":"10","ch.uzh.ciclassifier.features.configuration.ParseScore":"1","ch.uzh.ciclassifier.features.repository.NumberOfContributors":"590","ch.uzh.ciclassifier.features.configuration.NumberOfComments":"3","ch.uzh.ciclassifier.features.travisci.TimeToFixLatestAverage":"11252.625","ch.uzh.ciclassifier.features.github.OwnerType":"Organization","ch.uzh.ciclassifier.features.configuration.NumberOfNotifications":"0","ch.uzh.ciclassifier.features.travisci.ManualInteractionRatio":"0.0","ch.uzh.ciclassifier.features.repository.ProjectName":"pypa\/pip","ch.uzh.ciclassifier.features.repository.DaysUntilConfigAdded":"1227","ch.uzh.ciclassifier.features.configuration.LintScore":"0","ch.uzh.ciclassifier.features.configuration.EnvSize":"2","ch.uzh.ciclassifier.features.configuration.UseDeploy":"0","ch.uzh.ciclassifier.features.configuration.NumberOfJobs":"5","ch.uzh.ciclassifier.features.configuration.NumberOfConfigurationChars":"516","ch.uzh.ciclassifier.features.travisci.BuildTimeAverage":"7813.60221418393","ch.uzh.ciclassifier.features.configuration.UniqueInstructions":"3","ch.uzh.ciclassifier.features.repository.CommitsUntilConfigAdded":"1163","ch.uzh.ciclassifier.features.configuration.NumberOfStages":"2","ch.uzh.ciclassifier.features.travisci.PullRequestRatio":"0.7529710740713058","ch.uzh.ciclassifier.features.configuration.UseBranches":"0","ch.uzh.ciclassifier.features.github.PrimaryLanguage":"Python","ch.uzh.ciclassifier.features.repository.ConfigChangeFrequency":"0.011867859357010008","ch.uzh.ciclassifier.features.travisci.TimeToFixAverage":"10299.377040261154"},"types":["REPOSITORY","CONFIGURATION","GITHUB","TRAVISCI"],"db-identifier":"9e756dff-a048-4ec8-bf33-8c86b3cff27d"}