{"identifier":"ipfs_js-ipfs","features":{"ch.uzh.ciclassifier.features.travisci.BuildTimeLatestAverage":"20256.12","ch.uzh.ciclassifier.features.repository.NumberOfConfigurationFileChanges":"110","ch.uzh.ciclassifier.features.configuration.UseCache":"0","ch.uzh.ciclassifier.features.repository.NumberOfContributorsOnConfigurationFile":"8","ch.uzh.ciclassifier.features.travisci.BuildSuccessRatio":"0.28424265547500954","ch.uzh.ciclassifier.features.configuration.NumberOfConfigurationLines":"364","ch.uzh.ciclassifier.features.configuration.TemplateSimilarity":"14","ch.uzh.ciclassifier.features.configuration.ParseScore":"1","ch.uzh.ciclassifier.features.repository.NumberOfContributors":"235","ch.uzh.ciclassifier.features.configuration.NumberOfComments":"27","ch.uzh.ciclassifier.features.travisci.TimeToFixLatestAverage":"111696.36842105263","ch.uzh.ciclassifier.features.github.OwnerType":"Organization","ch.uzh.ciclassifier.features.configuration.NumberOfNotifications":"0","ch.uzh.ciclassifier.features.travisci.ManualInteractionRatio":"0.0","ch.uzh.ciclassifier.features.repository.ProjectName":"ipfs\/js-ipfs","ch.uzh.ciclassifier.features.repository.DaysUntilConfigAdded":"566","ch.uzh.ciclassifier.features.configuration.LintScore":"0","ch.uzh.ciclassifier.features.configuration.EnvSize":"1","ch.uzh.ciclassifier.features.configuration.UseDeploy":"0","ch.uzh.ciclassifier.features.configuration.NumberOfJobs":"58","ch.uzh.ciclassifier.features.travisci.BuildTimeAverage":"17731.323666978486","ch.uzh.ciclassifier.features.configuration.NumberOfConfigurationChars":"12682","ch.uzh.ciclassifier.features.configuration.UniqueInstructions":"59","ch.uzh.ciclassifier.features.repository.CommitsUntilConfigAdded":"594","ch.uzh.ciclassifier.features.configuration.NumberOfStages":"5","ch.uzh.ciclassifier.features.configuration.UseBranches":"1","ch.uzh.ciclassifier.features.travisci.PullRequestRatio":"0.8037238169123352","ch.uzh.ciclassifier.features.github.PrimaryLanguage":"JavaScript","ch.uzh.ciclassifier.features.repository.ConfigChangeFrequency":"0.018465670639583685","ch.uzh.ciclassifier.features.travisci.TimeToFixAverage":"94276.05388272583"},"types":["REPOSITORY","CONFIGURATION","GITHUB","TRAVISCI"],"db-identifier":"28110457"}