{"identifier":"OLC-Bioinformatics_StrainChoosr","features":{"ch.uzh.ciclassifier.features.travisci.BuildTimeLatestAverage":"232.45","ch.uzh.ciclassifier.features.repository.NumberOfConfigurationFileChanges":"13","ch.uzh.ciclassifier.features.configuration.UseCache":"1","ch.uzh.ciclassifier.features.repository.NumberOfContributorsOnConfigurationFile":"1","ch.uzh.ciclassifier.features.travisci.BuildSuccessRatio":"0.6060606060606061","ch.uzh.ciclassifier.features.configuration.NumberOfConfigurationLines":"27","ch.uzh.ciclassifier.features.configuration.TemplateSimilarity":"10","ch.uzh.ciclassifier.features.configuration.ParseScore":"2","ch.uzh.ciclassifier.features.configuration.NumberOfComments":"2","ch.uzh.ciclassifier.features.repository.NumberOfContributors":"2","ch.uzh.ciclassifier.features.travisci.TimeToFixLatestAverage":"0.0","ch.uzh.ciclassifier.features.github.OwnerType":"Organization","ch.uzh.ciclassifier.features.configuration.NumberOfNotifications":"0","ch.uzh.ciclassifier.features.travisci.ManualInteractionRatio":"0.0","ch.uzh.ciclassifier.features.repository.ProjectName":"OLC-Bioinformatics\/StrainChoosr","ch.uzh.ciclassifier.features.repository.DaysUntilConfigAdded":"55","ch.uzh.ciclassifier.features.configuration.LintScore":"0","ch.uzh.ciclassifier.features.configuration.EnvSize":"1","ch.uzh.ciclassifier.features.configuration.UseDeploy":"0","ch.uzh.ciclassifier.features.configuration.NumberOfJobs":"2","ch.uzh.ciclassifier.features.configuration.NumberOfConfigurationChars":"407","ch.uzh.ciclassifier.features.travisci.BuildTimeAverage":"232.45","ch.uzh.ciclassifier.features.configuration.UniqueInstructions":"6","ch.uzh.ciclassifier.features.repository.CommitsUntilConfigAdded":"16","ch.uzh.ciclassifier.features.configuration.NumberOfStages":"1","ch.uzh.ciclassifier.features.travisci.PullRequestRatio":"0.0","ch.uzh.ciclassifier.features.configuration.UseBranches":"1","ch.uzh.ciclassifier.features.github.PrimaryLanguage":"Python","ch.uzh.ciclassifier.features.repository.ConfigChangeFrequency":"0.2653061224489796","ch.uzh.ciclassifier.features.travisci.TimeToFixAverage":"110959.0"},"types":["REPOSITORY","CONFIGURATION","GITHUB","TRAVISCI"],"db-identifier":"123461669"}