{"identifier":"samrap_acf-fluent","features":{"ch.uzh.ciclassifier.features.travisci.BuildTimeLatestAverage":"153.56","ch.uzh.ciclassifier.features.repository.NumberOfConfigurationFileChanges":"7","ch.uzh.ciclassifier.features.configuration.UseCache":"0","ch.uzh.ciclassifier.features.repository.NumberOfContributorsOnConfigurationFile":"1","ch.uzh.ciclassifier.features.travisci.BuildSuccessRatio":"0.9306930693069307","ch.uzh.ciclassifier.features.configuration.NumberOfConfigurationLines":"11","ch.uzh.ciclassifier.features.configuration.TemplateSimilarity":"13","ch.uzh.ciclassifier.features.configuration.ParseScore":"2","ch.uzh.ciclassifier.features.repository.NumberOfContributors":"2","ch.uzh.ciclassifier.features.configuration.NumberOfComments":"0","ch.uzh.ciclassifier.features.travisci.TimeToFixLatestAverage":"0.0","ch.uzh.ciclassifier.features.github.OwnerType":"User","ch.uzh.ciclassifier.features.configuration.NumberOfNotifications":"0","ch.uzh.ciclassifier.features.travisci.ManualInteractionRatio":"0.0","ch.uzh.ciclassifier.features.repository.ProjectName":"samrap\/acf-fluent","ch.uzh.ciclassifier.features.repository.DaysUntilConfigAdded":"0","ch.uzh.ciclassifier.features.configuration.LintScore":"0","ch.uzh.ciclassifier.features.configuration.EnvSize":"0","ch.uzh.ciclassifier.features.configuration.UseDeploy":"0","ch.uzh.ciclassifier.features.configuration.NumberOfJobs":"2","ch.uzh.ciclassifier.features.travisci.BuildTimeAverage":"151.95555555555555","ch.uzh.ciclassifier.features.configuration.NumberOfConfigurationChars":"162","ch.uzh.ciclassifier.features.configuration.UniqueInstructions":"2","ch.uzh.ciclassifier.features.repository.CommitsUntilConfigAdded":"0","ch.uzh.ciclassifier.features.configuration.NumberOfStages":"1","ch.uzh.ciclassifier.features.configuration.UseBranches":"0","ch.uzh.ciclassifier.features.travisci.PullRequestRatio":"0.36538461538461536","ch.uzh.ciclassifier.features.github.PrimaryLanguage":"PHP","ch.uzh.ciclassifier.features.repository.ConfigChangeFrequency":"0.07368421052631578","ch.uzh.ciclassifier.features.travisci.TimeToFixAverage":"-216033.66666666666"},"types":["REPOSITORY","CONFIGURATION","GITHUB","TRAVISCI"],"db-identifier":"57268196"}